LICENSE
README.md
__init__.py
aioton.py
setup.py
aioton.egg-info/PKG-INFO
aioton.egg-info/SOURCES.txt
aioton.egg-info/dependency_links.txt
aioton.egg-info/top_level.txt