Metadata-Version: 2.1
Name: aioton
Version: 0.1
Summary: Working with TON API
Home-page: https://github.com/gfnprodev/aioton
Author: gfnpro
Author-email: gfnpro.dev@gmail.com
License: GPL-3.0 License
Platform: UNKNOWN
License-File: LICENSE
